{
  "_commit": "9e3c49f6680d4c400567c39d70b768f0a322c95e",
  "_copy_without_render": [
    "*.rst_t"
  ],
  "_jinja2_env_vars": {
    "lstrip_blocks": true,
    "trim_blocks": true
  },
  "_template": "https://github.com/statisticsnorway/ssb-pypitemplate.git",
  "author": "Magnus Theodor Engh",
  "code_quality_level": "Medium",
  "copyright_owner": "Statistics Norway",
  "copyright_year": "2025",
  "department_number": "",
  "dependency_manager_tool": "poetry",
  "development_status": "Development Status :: 4 - Beta",
  "email": "dor@ssb.no",
  "friendly_name": "SSB Dash Framework",
  "github_organization": "statisticsnorway",
  "license": "GPL-3.0",
  "package_name": "ssb_dash_framework",
  "project_name": "ssb-dash-framework",
  "version": "0.0.0"
}
